audrey_math/__init__.py
audrey_math/add.py
audrey_math/divide.py
audrey_math/multiply.py
audrey_math/subtract.py
audrey_math/extras/__init__.py
audrey_math/extras/divide.py
audrey_math/extras/multiply.py
audrey_math-0.0.5.dist-info/METADATA
audrey_math-0.0.5.dist-info/WHEEL
audrey_math-0.0.5.dist-info/top_level.txt
audrey_math-0.0.5.dist-info/RECORD
