Metadata-Version: 2.1
Name: audrey-math
Version: 0.0.5
Summary: first python package!
Author: Audrey Lin
Keywords: python,first package
